{
  "common": {
    "communityId": "社群ID",
    "cancel": "取消",
    "maximize": "最大化",
    "minimize": "最小化",
    "close": "關閉",
    "search": "搜尋",
    "help": "幫助",
    "new": "新的",
    "add": "新增",
    "edit": "編輯",
    "modify": "修改",
    "save": "儲存",
    "confirm": "確認",
    "reset": "重設",
    "undo": "撤銷",
    "actions": "操作",
    "id": "ID",
    "apply": "應用",
    "status": "狀態",
    "uploader": "圖片上傳（最大5MB）",
    "upload": "上傳圖片",
    "remove": "移除",
    "enabled": "啟用",
    "activeServer": "活躍中的伺服器",
    "success": "成功",
    "failed": "失敗",
    "tutorial": "教學",
    "tutorials": "教程",
    "refresh": "重新整理",
    "autoSort": "自動排序",
    "type": "型別",
    "itemsPerPage": "每頁顯示數量",
    "noData": "無資料",
    "noResults": "無結果",
    "externalWindow": "在外部窗中開啟",
    "lostConnection": "您與伺服器斷開連線。",
    "serverStatus": "伺服器狀態",
    "import": "上傳",
    "importPrompt": "貼上JSON內容",
    "export": "輸出",
    "learnMore": "更多資訊",
    "copy": "複製",
    "paste": "黏貼",
    "icon": "圖示",
    "test": "測試",
    "start": "開始",
    "pause": "暫停",
    "range": "範圍",
    "equal": "等於",
    "notEqual": "不等於",
    "contains": "包含",
    "errors": {
      "limitReached": "錯誤：已達到最大限制"
    }
  },
  "sideMenu": {
    "buttons": {
      "settings": "設定",
      "login": "登入",
      "logout": "登出",
      "communityMenu": "社群選單",
      "switchCommunities": "更換其他社群",
      "downloads": "下載",
      "tutorials": "教程",
      "myAccount": "我的賬號",
      "goFullscreen": "全屏化",
      "exitFullscreen": "退出全屏",
      "disclaimer": "如你訪問或使用Sonoran CAD，則代表您同意我們的條款和條件以及隱私政策。",
      "menu": "選單"
    }
  },
  "settings": {
    "settings": "設定",
    "volume": "音量",
    "helpImprove": "幫助改進翻譯",
    "language": "語言",
    "voice": "語音",
    "apiIdDisable": "你必須登入到社群才能設定API ID",
    "secretDisable": "你必須登陸倒社群才能獲取你的Secret ID",
    "hotkeys": "自定義按鍵",
    "hotkeyDisable": "免費版無法使用自定義按鍵設定",
    "prefix": "字首",
    "panic": "緊急狀況",
    "lockWindow": "鎖定視窗",
    "unlockWindow": "解鎖視窗",
    "quickResize": "快速縮放",
    "exitResize": "退出縮放",
    "classicLayout": "經典佈局",
    "resetLayout": "重置佈局",
    "bringToTop": "設為置頂",
    "showHide": "顯示/隱藏",
    "overlay": {
      "streamOverlay": "直播遮蔽",
      "credentials": "證書",
      "configuration": "配置",
      "twitchLogs": "Twitch記錄",
      "twitchConfig": "Twitch配置",
      "refreshPayment": "重新整理交易",
      "channel": "頻道",
      "oauthToken": "OAuth令牌",
      "obsTextFiles": "OBS文字檔案",
      "unitUpdates": "單位更新",
      "callUpdates": "呼叫更新",
      "twitch": "Twitch",
      "txtFiles": "文字檔案",
      "fileName": "檔名",
      "field": "區域",
      "customTextFiles": "自定義文字檔案",
      "dataKeys": "資料鍵",
      "events": "事件",
      "bodycam": "記錄儀",
      "confirmReset": "你確定要重置？",
      "lighting": "燈光",
      "addFrame": "新增框架",
      "addBulb": "新增燈泡",
      "delay": "延遲",
      "scanForBulbs": "掃描燈泡",
      "bulbType": "燈泡型別",
      "scan": "掃描",
      "manualIp": "手動設定IP (可選）"
    }
  },
  "taskbar": {
    "system": "系統",
    "newWindow": "新視窗",
    "pinToTaskbar": "固定至工作列",
    "unpinFromTaskbar": "從工作列解鎖",
    "taskbarPosition": "工作列位置",
    "tabCustomization": "自定義標籤頁",
    "displayTabIcons": "顯示標籤頁圖示",
    "displayTabLabels": "顯示標籤頁名稱",
    "layoutCustomization": "自定義佈局",
    "startMenu": "開始選單"
  },
  "login": {
    "buttons": {
      "login": "登入",
      "forgot": "忘記密碼",
      "create": "建立賬號",
      "cancel": "取消",
      "staySignedIn": "保持登入",
      "switchCommunities": "切換到其他社群"
    },
    "labels": {
      "email": "電子郵件",
      "username": "使用者名稱",
      "password": "密碼",
      "confirmPassword": "確認密碼",
      "emailPreferences": "Email偏好",
      "resetPassword": "重設密碼"
    }
  },
  "selectionPage": {
    "buttons": {
      "myCommunities": "您的社群資訊",
      "joinCommunity": "進入社群",
      "discover": "探索",
      "leaveCommunity": "離開社群",
      "createCommunity": "建立社群",
      "My Account": "我的賬號"
    },
    "labels": {
      "communityName": "社群名稱",
      "website": "網頁 (可選項)"
    },
    "text": {
      "joinHeader": "加入一個社群",
      "joinText": "加入現有的社群CAD！",
      "createHeader": "CAD註冊",
      "createText": "註冊新的社群CAD供其他人加入！",
      "helpCommunityId1": "您的社群ID是您的社群的唯一的身份認證。這是使用者將用來登入您個人CAD系統的憑證。",
      "helpCommunityId2": "一般情況下，這會您的社群的縮寫。",
      "helpCommunityId3": "例如：安寧守護者伺服器 - ID：GOPDOJ",
      "helpCommunityName": "您的社群名稱是您的角色扮演社群的公共名稱。",
      "helpCommunityWebsite": "您的社群網站是您的論壇，論壇或其他網站的URL。該欄位是可選項。",
      "confirmLeave1": "您確定要離開此社群嗎？",
      "confirmLeave2": "您的帳戶和此CAD上的所有資料將被刪除！",
      "communityNotFound": "未找到此社群",
      "helpCommunityIdFindHeader": "在哪裡可以找到我的社群ID？",
      "helpCommunityIdFind1": " 您必須與遊戲社群的成員或管理員聯絡。",
      "helpCommunityIdFind2": "他們將為您提供其CAD的特定社群ID。"
    },
    "tooltips": {
      "leaveCommunity": "離開此社群。",
      "owner": "你擁有此社群。",
      "search": "搜尋Sonoran CAD社群。",
      "register": "註冊您的Sonoran CAD賬戶",
      "joinHelp": "不確定該怎麼辦？",
      "joinThis": "加入這個社群CAD。",
      "join": "加入"
    },
    "errors": {
      "noCommunityID": "錯誤：請輸入社群ID！",
      "communityIdLength": "錯誤：您的社群ID必須介於1到50個字元之間！",
      "communityIdCharacters": "錯誤：您的社群ID只能包含字母，數字，下劃線和破折號！",
      "communityNameLength": "錯誤：您的社群名稱必須在1到50個字元之間！"
    }
  },
  "account": {
    "labels": {
      "myAccount": "我的賬號",
      "email": "電子郵件",
      "username": "使用者名稱",
      "emailPreferences": "Email偏好",
      "confirmPassword": "確認密碼",
      "emailMe": "透過電子郵件將重要的公告，更新和促銷傳送給我。"
    },
    "buttons": {
      "subscriptions": "訂閱內容"
    },
    "errors": {
      "passwordLength": "錯誤：您的密碼必須大於5個字元！",
      "passwordNumber": "錯誤：密碼必須至少包含一個大寫字母和一個數字！",
      "passwordMatch": "錯誤：您的密碼不匹配！"
    }
  },
  "payment": {
    "text": {
      "setCommunityId": "設定社群ID",
      "newSubscription": "新訂閱",
      "bundleAndSave": "捆綁並儲存",
      "serversEmail": "Sonoran伺服器帳戶電子郵件",
      "serverIp": "伺服器IP",
      "bundleExplain": "從Sonoran伺服器購買VPS時，每月可節省30％。"
    },
    "labels": {
      "plan": "套餐",
      "startDate": "開始日期",
      "endDate": "結束日期",
      "starter": "基礎版",
      "standard": "標準版",
      "plus": "高階版",
      "pro": "專業版",
      "expertInstallation": "專家安裝"
    },
    "buttons": {
      "purchase": "申購",
      "comparePlans": "套餐對比",
      "oneTimePurchases": "一次性購買",
      "amount": "金額"
    }
  },
  "communityMenu": {
    "buttons": {
      "civilian": "市民",
      "dmv": "車管局",
      "law": "法務",
      "police": "警察",
      "fire": "消防",
      "ems": "急救員",
      "dispatch": "調度中心",
      "admin": "管理員",
      "discord": "Discord",
      "website": "網頁",
      "setDefault": "設定預設社群"
    },
    "labels": {
      "permissionKey": "許可權金鑰"
    }
  },
  "civilian": {
    "buttons": {
      "newCharacter": "新建市民",
      "editCharacter": "編輯市民",
      "records": "記錄",
      "dmv": "車管局"
    },
    "characterEditor": {
      "first": "名",
      "last": "姓",
      "mi": "中間名縮寫",
      "dob": "出生日期",
      "age": "年齡",
      "sex": "性別",
      "aka": "A.K.A.（曾用名/已知的暱稱）",
      "residence": "住宅地址",
      "zip": "郵編座標",
      "occupation": "職業",
      "height": "身高",
      "weight": "體重",
      "skin": "膚色",
      "hair": "髮色",
      "eye": "瞳色",
      "emergencyContact": "緊急聯絡人",
      "relationship": "關係",
      "contactNumber": "聯絡電話",
      "image": "照片",
      "addCharacter": "新增市民",
      "saveCharacter": "儲存市民",
      "removeCharacter": "移除市民",
      "createNewCharacter": "建立一個新的市民",
      "editExistingCharacter": "編輯市民",
      "confirmRemove": "你確定你要移除這個市民嗎？"
    },
    "labels": {
      "selectedCharacter": "選擇市民"
    },
    "errors": {
      "maxCharacters": "錯誤：您已達到社群的最大字元數限制"
    }
  },
  "police": {
    "lookup": {
      "lookup": "查詢",
      "sendToUnits": "傳送至單位",
      "partial": "部分",
      "exact": "精確",
      "reportsHeader": "報告",
      "identifier": "員警身份",
      "id": "記錄ID",
      "newLookup": "新的查詢",
      "refresh": "重新整理",
      "nameSearch": "搜尋名字",
      "first": "名",
      "last": "姓",
      "mi": "中間名首字母",
      "plateSearch": "搜尋車牌",
      "plate": "車牌資訊",
      "agency": "機構",
      "department": "部門",
      "unit": "單位",
      "civilians": "市民",
      "records": "記錄",
      "noRecordsFound": "未找到任何記錄",
      "recordsPerPage": "每頁記錄數",
      "recordsNoData": "沒有可用的記錄",
      "recordsNoResults": "未找到任何記錄",
      "statuses": {
        "active": "啟用",
        "inactive": "閒置",
        "closed": "關閉"
      },
      "columns": {
        "name": "名字",
        "plate": "車牌",
        "charges": "指控",
        "flags": "標記",
        "date": "日期",
        "status": "狀態",
        "type": "種類",
        "expiration": "到期時間",
        "first": "名",
        "last": "姓",
        "mi": "中間名縮寫"
      },
      "alerts": {
        "emptySearch": "錯誤：空白搜尋！"
      },
      "getOwner": "獲取所有者"
    },
    "records": {
      "general": {
        "records": "記錄",
        "reports": "報告"
      },
      "editor": {
        "recordType": "記錄種類",
        "dmvType": "車輛登記種類",
        "addRecord": "新增記錄",
        "saveRecord": "儲存記錄",
        "removeRecord": "移除記錄",
        "pdf": "PDF",
        "applyForDmv": "申請車管局備案",
        "copyLink": "複製記錄連結",
        "pasteLink": "貼上記錄連結",
        "linkTitle": "鏈接主題",
        "noCustomTypes": "無記錄型別：請在管理員>自定義>自定義記錄中進行新增",
        "status": {
          "active": "正在處理",
          "closed": "已結案",
          "pending": "待處理",
          "approved": "已通過",
          "rejected": "已拒絕"
        },
        "errors": {
          "requiredField": "錯誤：有必填項為空",
          "nameOrPlate": "錯誤：此專案必須包含要搜尋的市民名字或車牌！",
          "noName": "錯誤：此專案必須包含要搜尋的市民名字！",
          "noPlate": "錯誤：此專案必須包含要搜尋的車牌！",
          "noCopiedLink": "錯誤：您沒有複製記錄連結！"
        }
      },
      "agency": {
        "agencyInformation": "機構資訊",
        "agencyName": "機構名稱",
        "recordNum": "記錄編號",
        "date": "日期",
        "observingOfficer": "觀察員",
        "location": "地址",
        "zip": "郵政編碼",
        "badge": "警號"
      },
      "getCiv": {
        "characterSearch": "市民搜尋",
        "civilianInfo": "市民資訊"
      },
      "getVeh": {
        "vehicleSearch": "車輛搜尋"
      },
      "narrative": {
        "narrative": "事件經過"
      },
      "charges": {
        "charges": "指控",
        "charge": "指控",
        "chargeNumber": "指控編號",
        "fineTotal": "待繳金額：",
        "chargeType": "指控型別",
        "counts": "次數",
        "titleCode": "法律條目",
        "bondType": "保釋型別",
        "bondFineAmount": "保釋金/罰款金額",
        "jailTime": "監禁時長"
      },
      "speed": {
        "citationInformation": "罰單資訊",
        "vehicleSpeed": "車速",
        "speedLimit": "速度限制",
        "paceType": "測速方法",
        "courtDate": "開庭日期",
        "courtTime": "開庭時間",
        "fine": "罰款",
        "pace": "跟隨測速",
        "radar": "雷達測速",
        "other": "其他"
      },
      "status": {
        "status": "狀態",
        "dateSubmitted": "提交日期",
        "supervisorSignature": "主管簽名",
        "observingSignature": "觀察員簽名"
      },
      "vehicle": {
        "vehicleInformation": "車輛資訊",
        "type": "車輛型別",
        "plate": "車牌",
        "make": "品牌",
        "model": "型號",
        "color": "顏色",
        "year": "年份",
        "types": {
          "sedan": "四門轎車",
          "coupe": "雙門轎車",
          "suv": "SUV",
          "truck": "卡車",
          "offroad": "越野車",
          "marine": "船隻",
          "motorcycle": "摩托車",
          "aircraft": "飛機"
        }
      },
      "arrest": {
        "arrestInformation": "逮捕資訊",
        "weapons": "武器",
        "arrestType": "逮捕型別",
        "probationaryOfficer": "假釋官"
      }
    },
    "recordCenter": {
      "myFiles": "我的檔案",
      "newReport": "新建報告",
      "newRecord": "新建記錄",
      "supervisorPanel": "主管頁面",
      "pendingRecords": "待處理記錄",
      "filesAwaitingApproval": "待審批檔案",
      "pendingFiles": "待處理檔案",
      "noReportsForSuper": "沒有需要主管操作的報告",
      "noReportsFound": "未找到報告",
      "noRecordsForSuper": "沒有需要主管操作的記錄",
      "noRecordsFound": "未找到記錄",
      "errors": {
        "noRecordTypes": "無記錄型別：請在管理員>自定義>自定義記錄中進行新增",
        "noReportTypes": "無報告型別：請在管理員>自定義>自定義記錄中進行新增",
        "syncEnabledFeatDisabled": "此功能與數據庫同步不兼容"
      }
    },
    "callEditor": {
      "newDispatch": "新建排程",
      "savedTypes": "已保存的類型",
      "dispatch": "排程",
      "callViewer": "瀏覽呼叫",
      "createCall": "建立呼叫",
      "updateCall": "更新呼叫",
      "clearEditor": "清空編輯器",
      "selfDispatch": "自我派遣",
      "selfClear": "自我清除",
      "units": "單位",
      "callOrigin": "呼叫型別",
      "callStatus": "呼叫狀態",
      "priority": "優先順序",
      "block": "街區",
      "address": "地址",
      "postal": "郵政編碼",
      "callTitle": "呼叫標題",
      "code": "10-Code程式碼",
      "primaryUnit": "主處理單位",
      "callDescription": "呼叫描述",
      "callNotes": "呼叫備註",
      "note": "備註",
      "addNote": "新增備註",
      "dispatchRecord": "排程記錄",
      "trackPrimary": "追蹤主處理單位（GPS）",
      "confirmations": {
        "close1": "您必須將呼叫狀態設定為關閉。",
        "close2": "您確定要關閉此呼叫嗎？",
        "close3": "此呼叫和其資料將被刪除！",
        "detatch": "脫離呼叫",
        "detatchConfirm": "確定要脫離當前呼叫嗎？"
      },
      "statusOptions": {
        "pending": "掛起",
        "active": "活躍",
        "closed": "關閉"
      },
      "originOptions": {
        "caller": "911報警",
        "radioDispatch": "員警無線電報警",
        "observed": "員警目擊",
        "walkUp": "警局內報案"
      },
      "errors": {
        "unitAlreadyOnCall": "錯誤：此單位正在響應其他呼叫！",
        "noOrigin": "錯誤：此呼叫未設定型別！",
        "noStatus": "錯誤：此呼叫未設定狀態！",
        "noPriority": "錯誤：此呼叫未設定優先順序！",
        "noTitle": "錯誤：此呼叫未設定標題！",
        "attachedAlready": "錯誤：您已經在響應其他呼叫了！"
      },
      "nearestUnits": "Najbliższe Jednostki",
      "nearestStations": "Najbliższe stacje"
    },
    "callList": {
      "activeCalls": "活躍呼叫",
      "callHistory": "歷史呼叫",
      "editCall": "編輯呼叫",
      "attachToCall": "關聯呼叫",
      "previewCall": "預覽呼叫",
      "closeCall": "關閉呼叫",
      "printCall": "列印呼叫",
      "priority": "優先順序",
      "columns": {
        "callId": "呼叫ID",
        "10Code": "10-Code程式碼",
        "callTitle": "呼叫標題",
        "address": "地點",
        "units": "單位",
        "status": "狀態"
      }
    },
    "emergencyCall": {
      "emergencyCall": "緊急呼叫",
      "emergency": "緊急",
      "civil": "平民",
      "calls": "呼叫",
      "caller": "報警人",
      "location": "地點",
      "description": "描述",
      "removeAll": "關閉所有活躍的緊急呼叫",
      "openInEditor": "在編輯器中開啟呼叫",
      "removeCall": "移除呼叫",
      "removeAllCalls": "移除所有呼叫",
      "confirmRemoveAll": "您確定要關閉所有活躍的緊急呼叫嗎？"
    },
    "header": {
      "signalEffect1": "訊號",
      "signalEffect2": "已生效",
      "activeServer": "當前伺服器",
      "lookup": "查詢",
      "records": "記錄",
      "bolo": "BOLO資訊",
      "liveMap": "線上地圖",
      "quickLinks": "快速連結",
      "signal": "訊號",
      "activeUnits": "活躍單位",
      "activeCalls": "活躍呼叫",
      "emergencyCalls": "緊急呼叫",
      "panic": "緊急狀態",
      "file": "檔案",
      "toneBoard": "音效面板",
      "playTo": "播放至",
      "repeat": "重複",
      "seconds": "秒",
      "count": "計數",
      "streetSigns": "街道標識",
      "bodyCam": "Cámara Corporal"
    },
    "timers": {
      "timers": "計時器",
      "newTimer": "新計時器",
      "attachments": "附件",
      "clearAttachment": "清除附件"
    },
    "signal": {
      "signal": "訊號",
      "initiate": "啟用訊號",
      "modify": "編輯訊號",
      "clear": "清楚訊號"
    },
    "unitEditor": {
      "modifyIdentifier": "編輯員警身份",
      "unitNumber": "呼號",
      "name": "名稱",
      "rank": "職級",
      "status": "狀態",
      "location": "地點",
      "aop": "AOP",
      "agency": "機構",
      "group": "小組",
      "departments": "部門",
      "department": "部門",
      "subdivisions": "子部門",
      "subdivision": "子部門",
      "units": "單位",
      "switchIdentifier": "切換員警身份",
      "confirmRemove": "確定要刪除身份資訊嗎？"
    },
    "units": {
      "activeUnits": "活躍單位",
      "dispatchersShown": "DP顯示",
      "dispatchersHidden": "DP隱藏",
      "addToCall": "新增至呼叫",
      "addToGroup": "新增到小組",
      "newGroup": "新小組",
      "editUnit": "編輯單位",
      "togglePanic": "啟用緊急狀態",
      "kickUnit": "將單位踢出",
      "activeGroups": "活躍小組",
      "unitGroups": "單位小組",
      "groupName": "小組名稱",
      "createGroup": "建立小組",
      "group": "小組",
      "units": "單位"
    },
    "notes": {
      "notepad": "記事本",
      "title": "主題",
      "notes": "備註"
    },
    "command": {
      "commandLine": "命令行",
      "create": "創建",
      "close": "關閉",
      "attach": "響應",
      "detach": "脫離",
      "view": "查看",
      "clear": "清空",
      "status": "狀態",
      "note": "備註",
      "savedCallType": "保存的呼叫類型",
      "unit": "單位",
      "postal": "郵編",
      "callId": "呼叫ID",
      "unitStatus": "單位狀態"
    }
  },
  "admin": {
    "general": {
      "accounts": "賬戶",
      "customization": "自定義",
      "advanced": "進階",
      "permissionKeys": "許可權金鑰",
      "departments": "部門",
      "customRecords": "自定義記錄",
      "logs": "記錄",
      "inGameIntegration": "遊戲內整合功能",
      "discordIntegration": "DIscord整合功能",
      "limits": "限制",
      "wipeRecords": "清空記錄",
      "transferOrDelete": "轉移或刪除CAD",
      "changeCommunityId": "修改社群ID",
      "authenticate": "驗證"
    },
    "authenticate": {
      "authHeader": "驗證您的CAD所有權",
      "authSubtext1": "社群所有者可以請求唯一的標識金鑰來驗證其所有權。",
      "authSubtext2": "這用於請求支援團隊成員進行手動修改。",
      "requestCode": "請求程式碼"
    },
    "communityId": {
      "changeHeader": "更改您的社群ID",
      "changeSubtext1": "社群所有者可以請求新的社群ID。",
      "changeSubtext2": "CAD中的所有使用者都需要登出然後重新登入，以免出現問題。",
      "existingId": "當前ID",
      "newId": "新ID",
      "requestChange": "請求更改"
    },
    "customization": {
      "customizationHeader": "Sonoran CAD社群定製",
      "customizationSubtext1": "社群資訊",
      "customizationSubtext2": "自定義您的社群名稱，LOGO等！",
      "customizationDisabled": "您的版本不包含社群自定義功能。",
      "info": {
        "communityInfo": "社群資訊",
        "communityId": "社群ID",
        "name": "名稱",
        "subtitle": "子名稱",
        "website": "官方網站",
        "discord": "Discord",
        "voiceCommand": "呼號關鍵字",
        "timezone": "時區"
      },
      "geo": {
        "geographicalSettings": "地理設定",
        "geoSubtext": "根據您社群的地理位置將進行描述。",
        "emergencyCode": "緊急程式碼",
        "penalCodeName": "法典名稱",
        "tenCodeName": "10-Code程式碼名稱",
        "currencyDelimiter": "貨幣符號"
      },
      "unitStatus": {
        "unitStatusCodes": "單位狀態程式碼",
        "busy": "繁忙",
        "unavailable": "離開",
        "available": "可用",
        "enroute": "在途中",
        "onScene": "在現場"
      },
      "customLogin": {
        "customLoginPage": "自定義登入介面",
        "url": "URL"
      },
      "quickLinks": {
        "quickLinks": "快速連結",
        "newLink": "新連結",
        "deleteLink": "刪除連結",
        "label": "標籤",
        "link": "連結",
        "color": "顏色"
      },
      "notificationTones": {
        "notificationTones": "通知音效",
        "newDispatch": "新排程",
        "dispatchUpdated": "排程更新",
        "dispatchClosed": "排程結束",
        "statusChange": "狀態變更",
        "dispatchNote": "排程備註"
      },
      "emails": {
        "customEmails": "自定義社群電子郵件",
        "subtext1": "自定義使用者在建立帳戶或從您的自定義登入螢幕重置密碼時收到的電子郵件。",
        "accountRegistration": "使用者註冊",
        "viewTemplate": "檢視模板",
        "header": "標題",
        "subheader": "子標題",
        "body": "內容",
        "resetPassword": "重置密碼",
        "emailTemplate": "Email模板"
      },
      "pageColors": {
        "customPageColors": "自定義頁面顏色",
        "loginPageBkg": "登入頁面背景",
        "setToDefault": "設為預設顏色",
        "menuPageBkg": "選單頁面背景"
      },
      "restrictions": {
        "userAccountRestrictions": "使用者賬戶限制",
        "subtext1": "Sonoran CAD允許您限制每個使用者帳戶可以建立的市民、許可證和車輛註冊的數量。",
        "maxCivilians": "最高市民上限",
        "maxLicenses": "最高許可證上限 *",
        "maxRegistrations": "最高車輛註冊上限 *",
        "note": "* 這些限制不適用於啟用了資料庫同步的社群。"
      },
      "otherCustomization": "其他自定義功能",
      "servers": {
        "servers": "伺服器",
        "subtext1": "您的社群使用多個伺服器嗎？",
        "subtext2": "Sonoran CAD允許您分離線上單位並在多臺伺服器之間進行排程，同時仍共享相同的記錄。",
        "subtext3": "您的社群目前最多可以支援",
        "subtext4": "伺服器",
        "newServer": "新伺服器",
        "name": "名稱",
        "description": "描述"
      },
      "lookupTypes": {
        "lookupTypes": "查詢型別",
        "customRecordFieldId": "自定義記錄表ID"
      },
      "errors": {
        "serverLimit1": "錯誤：您的社群只允許設定",
        "serverLimit2": "伺服器！",
        "serverMinimum": "錯誤：您必須至少擁有一臺伺服器！"
      },
      "discordRpc": {
        "info1": "桌面使用者將在Discord顯示一個邀請按鈕。該按鈕可以連線至你的CAD或CMS申請表。",
        "discordRichPresence": "Discord富文字",
        "clientId": "使用者ID",
        "iconName": "圖示名稱",
        "btn2Failure": "錯誤：若無Pro訂閱，第二個按鈕只能將使用者導航至CAD或CMS邀請頁面。"
      }
    },
    "department": {
      "agencies": "機構",
      "agency": "機構",
      "departments": "部門",
      "department": "部門",
      "subdivisions": "子部門",
      "name": "名稱",
      "description": "描述",
      "abbreviation": "縮寫",
      "address": "地址",
      "zip": "郵政編碼",
      "errors": {
        "generalLimit1": "錯誤：您的社群只允許設定",
        "agencyLimit2": "機構！",
        "departmentLimit2": "部門在當前區域！",
        "subdivisionLimit2": "子部門在當前部門！",
        "agencyExists": "錯誤：使用此名稱的機構已經存在！",
        "districtExists": "錯誤：使用此名稱的區域已經存在！",
        "departmentExists": "錯誤：使用此名稱的部門已經存在！",
        "subdivisionExists": "錯誤：使用此名稱的子部門已經存在！"
      },
      "modifyDepartment": {
        "createNewDepartment": "建立新部門",
        "editDepartment": "編輯部門",
        "name": "部門名稱",
        "abbreviation": "縮寫",
        "address": "地址",
        "zip": "郵政編碼",
        "confirmRemove1": "確定要刪除此部門嗎？",
        "confirmRemove2": "此部門及其所有子部門已被刪除。"
      },
      "modifyAgency": {
        "createNewAgency": "建立新機構",
        "editAgency": "編輯機構",
        "name": "機構名稱",
        "description": "描述",
        "remove": {
          "confirmRemove1": "確定要刪除此機構嗎？",
          "confirmRemove2": "此機構及其所有部門和子部門已被刪除。"
        }
      },
      "modifySubdivision": {
        "createNewSub": "建立新子部門",
        "editSub": "編輯子部門",
        "name": "子部門名稱",
        "description": "描述",
        "confirmRemove": "確定要刪除此子部門嗎？"
      }
    },
    "webhooks": {
      "modified": "已編輯",
      "removed": "已刪除",
      "headerText": "Sonoran CAD Discord整合功能",
      "subtext1": "Sonoran CAD Discord整合功能可以將所有警報傳送到Discord伺服器。",
      "subtext2": "只需在下面的欄位中啟用並指定Discord推送URL。",
      "emergencyWebhooks": "緊急推送",
      "about": "關於",
      "emergencyAbout": "這些推送與緊急資訊有關。",
      "unitPanic": "單位緊急狀態",
      "unitPanicAbout": "在單位啟用其緊急狀態時，將傳送此推送。",
      "dispatch": "排程響應",
      "dispatchAbout": "在新增或修改排程響應時，將傳送此推送。",
      "policeRecord": "員警記錄",
      "policeRecordAbout": "新增，修改或刪除員警記錄時，將傳送此推送。",
      "medicalRecord": "急救記錄",
      "medicalRecordAbout": "新增，修改或刪除急救記錄時，將傳送此推送。",
      "fireRecord": "消防記錄",
      "fireRecordAbout": "新增，修改或刪除消防記錄時，將傳送此推送。",
      "bolo": "BOLO資訊",
      "boloAbout": "在新增或修改BOLO資訊時，將傳送此推送。",
      "emergencyCall": "緊急呼叫",
      "emergencyCallAbout": "在收到緊急呼叫時，將傳送此推送。",
      "civilianWebhooks": "市民資訊推送",
      "civilianWebhooksAbout": "此推送與市民資訊有關。",
      "character": "市民資訊變更",
      "characterAbout": "新增，修改或刪除市民資訊時，將傳送此推送。",
      "dmv": "車管局記錄",
      "dmvAbout": "新增，修改或刪除車管局記錄時，將傳送此推送。",
      "law": "法務記錄",
      "lawAbout": "新增，修改或刪除法務記錄時，將傳送此推送。",
      "adminWebhooks": "管理員推送",
      "adminWebhooksAbout": "此推送與管理員資訊有關。",
      "accountPermissions": "使用者許可權",
      "accountPermissionsAbout": "在修改使用者許可權時，將傳送此推送。",
      "departmentStructure": "部門架構",
      "departmentStructureAbout": "在修改部門架構時，將傳送此推送。",
      "10Code": "10-Code程式碼變更",
      "10CodeAbout": "新增，修改或刪除10-Code程式碼時，將傳送此推送。",
      "penalCode": "法律條目變更",
      "penalCodeAbout": "新增，修改或刪除法律條目時，將傳送此推送。",
      "apiRequest": "API申請",
      "apiRequestAbout": "在申請API時，將傳送此推送。",
      "signal": "代號",
      "signalAbout": "在啟用代號時，將傳送此推送。",
      "toneBoardAbout": "在DP播放一個音效時，該webhook將被髮送",
      "errors": {
        "maxWebhooks": "錯誤：已達到該社群可傳送推送的上限："
      }
    },
    "limits": {
      "limitsHeader": "Sonoran CAD社群限制",
      "upgradeYourCad": "升級您的CAD",
      "version": "版本",
      "expiration": "到期日"
    },
    "remove": {
      "removeWarning1": "刪除或轉讓CAD不會取消任何活躍的社群訂閱。",
      "removeWarning2": "您可以在支付中心取消訂閱或將訂閱轉移到另一個社群。",
      "transferHeader": "轉移您的Sonoran CAD",
      "transferSubtext": "您必須是該社群/CAD的所有者，才能轉讓此CAD。轉讓過程需要電子郵件驗證。",
      "transferCad": "轉讓CAD",
      "transferCadTo": "轉讓CAD給",
      "removeHeader": "刪除你的Sonoran CAD",
      "removeSubtext": "您必須是該社群/CAD的所有者，才能刪除此CAD。刪除過程需要電子郵件驗證。",
      "removeCad": "刪除CAD"
    },
    "wipeRecords": {
      "wipeHeader": "清空您的社群記錄",
      "wipeSubtext1": "社群所有者可以按型別刪除所有儲存的記錄。",
      "wipeSubtext2": "選擇下面的型別以刪除該型別的記錄。",
      "confirmWipe1": "確定要刪除所有型別的記錄嗎？",
      "confirmWipe2": "此操作無法撤銷！"
    },
    "accounts": {
      "userAccounts": "使用者賬戶",
      "username": "使用者名稱",
      "status": "狀態",
      "joined": "已加入",
      "permissions": "許可權",
      "lastLogin": "上次登入時間",
      "apiIds": "API ID",
      "purge": "清除不活躍使用者",
      "purgeConfirm": "您確定要清除所有不活躍超過30天的使用者帳戶嗎？"
    },
    "customRecords": {
      "existingHeader": "現有自定義記錄型別",
      "recordEditor": "記錄編輯器",
      "recordTypeName": "記錄型別名稱",
      "type": "型別",
      "resyncPreview": {
        "resyncPreview": "重新同步預覽字段",
        "confirm": "這將手動更新所有先前的記錄，以確保預覽的字段與您的最新記錄模板匹配。此動作保持 10 分鐘的冷卻時間。"
      },
      "addCustomSection": "新增自定義節",
      "addPremadeSection": "新增預設節",
      "recordSections": "記錄節",
      "newField": "新欄位",
      "searchCivs": "搜尋市民資訊",
      "searchVehicles": "搜尋車輛資訊",
      "enableDuplicate": "開啟克隆",
      "duplicateSection": "克隆區域",
      "sectionLabel": "節標籤",
      "lookupPreviewAbout": "在查詢表預覽中顯示欄位值",
      "supervisorAbout": "僅主管可用的欄位",
      "requiredAbout": "必填欄位",
      "uniqueField": "唯一欄位",
      "readOnly": "只讀",
      "newValue": "新資料",
      "reverseMap": "反向對映",
      "enableMapping": "啟用對映",
      "lookupPreview": "查詢預覽",
      "recordPreview": "預覽記錄",
      "actions": "操作",
      "name": "名稱",
      "mask": "掩碼",
      "label": "標籤",
      "width": "寬度",
      "dbMap": "資料庫同步對映",
      "dependency": "依賴",
      "dependencyInfo": {
        "infoEqual": "當字段相等時顯示：",
        "infoNotEqual": "當字段不相等時顯示：",
        "infoContains": "當字段包含一個或多個顯示："
      },
      "recordTypes": {
        "warrant": "通緝令",
        "bolo": "BOLO資訊",
        "license": "許可證資訊",
        "vehicleRegistration": "車輛註冊資訊",
        "policeRecord": "員警記錄",
        "policeReport": "員警報告",
        "medicalRecord": "急救記錄",
        "medicalReport": "急救報告",
        "fireRecord": "消防記錄",
        "fireReport": "消防報告",
        "dmvRecord": "車管局記錄",
        "lawRecord": "法務記錄",
        "lawReport": "法務報告"
      },
      "errors": {
        "maxCiv": "錯誤：此記錄型別具有太多可搜尋的使用者欄位（UID為'first'和'last'的欄位）。",
        "minCiv": "錯誤：此記錄型別沒有足夠可搜尋的使用者欄位（UID為“ first”和“ last”的欄位）。",
        "maxVeh": "錯誤：此記錄型別可搜尋的車輛欄位過多（UID為'plate'的欄位）。",
        "minVeh": "錯誤：此記錄型別沒有足夠可搜尋的車輛欄位（UID為'plate'的欄位）。",
        "maxStatus": "錯誤：此記錄型別具有太多自定義型別的'status'欄位。",
        "minStatus": "錯誤：此記錄型別必須具有一個自定義型別的'status'欄位。",
        "noStatusField": "錯誤：此記錄型別必須具有一個UID為'status'欄位。",
        "noPreviewedFields": "錯誤：此記錄模板沒有啟用預覽的欄位。",
        "noName": "錯誤：此記錄模板未設定名稱。"
      },
      "remove": {
        "removeType": "移除記錄型別",
        "confirmRemove": "確定要移除這個記錄型別嗎？"
      }
    },
    "integration": {
      "apiHeader": "網頁API",
      "apiSubheader": "Sonoran CAD的網頁API允許您實時更新單位的位置、切換單位的緊急狀態、生成緊急呼叫，以及在遊戲中進行更多操作！",
      "resources": "資源",
      "apiKey": "API金鑰",
      "changeApiKey": "修改API金鑰",
      "apiDocs": "API文件",
      "luaPlugins": "LUA外掛",
      "confirmKeyChange1": "確定要申請新的API金鑰嗎？",
      "confirmKeyChange2": "您需要在所有外掛或API配置中更新您的API金鑰！",
      "liveMapHeader": "伺服器事件和整合實時地圖",
      "liveMapSubtext1": "Sonoran CAD的實時地圖配置使您可以立即設定社群的自定義整合實時地圖，我們甚至可以託管您的伺服器！",
      "liveMapSubtext2": "Sonoran CAD還可以將事件資料推送到您配置的偵聽器埠。",
      "mapTutorial": "地圖教程",
      "eventDocumentation": "事件記錄",
      "configureAndDeploy": "配置並部署",
      "enableMap": "啟用地圖",
      "staticOnly": "只使用靜態URL",
      "staticOnlyAbout": "如果您的遊戲模式與實時地圖資源不相容，則可以指定一個帶有遊戲地圖的網站。",
      "mapType": "地圖型別",
      "uploadCustomMap": "上傳自定義地圖",
      "server": "伺服器",
      "ip": "IP",
      "websiteUrl": "網站URL",
      "mapPort": "地圖埠",
      "gamePort": "遊戲埠",
      "differingOutboundIp": "不同的出站IP",
      "outboundIp": "出站IP",
      "saveAndDeploy": "儲存並部署",
      "dbSync": {
        "dbSyncHeader": "資料庫同步",
        "dbSyncSubtext1": "Sonoran CAD的資料庫同步功能允許您將市民資訊、許可證資訊和車輛註冊資訊直接從遊戲資料庫中提取到CAD。",
        "dbSyncSubtext2": "只需修改資料庫SQL連線的字串，然後將表和欄位對映到Sonoran CAD即可。",
        "dbSyncSubtext3": "所有紅色欄位均為必填項。如果可選欄位的無需新增資料，則將其保留為空白。",
        "connectionCredentials": "SQL連線憑證",
        "description": "描述",
        "descriptionCredentials": "在這裡填寫您伺服器的SQL連線憑證。",
        "enableDbSync": "啟用資料庫同步",
        "enableDbMerge": "啟用資料庫整合",
        "testConnection": "測試連線",
        "saveCredentials": "儲存連線憑證",
        "type": "型別",
        "host": "伺服器地址",
        "port": "埠",
        "database": "資料庫名",
        "username": "使用者名稱",
        "password": "密碼",
        "characterMapping": "市民資訊對映",
        "licenseMapping": "許可證資訊對映",
        "vehicleMapping": "車輛資訊對映",
        "testMapping": "對映測試",
        "saveMapping": "儲存對映設定",
        "tableName": "表名",
        "characterMappingColumn": "市民資訊列對映",
        "customMapAbout": "自定義記錄編輯器內有關資料的資料庫同步對映資訊。",
        "columnName": "資料庫列名",
        "externalKey": "外部金鑰",
        "jsonKey": "JSON金鑰",
        "jsonColumn": "JSON列名",
        "jsonColumnAbout": "如果此列是JSON資料型別，則可以指定JSON金鑰。",
        "label": "標籤",
        "tooltipLabel": "資料庫欄位描述。",
        "tooltipColumn": "資料庫表中包含該欄位的資料庫列的名稱。",
        "tooltipTable": "該資料庫列所在的資料庫表名。 ",
        "tooltipCharacterColumn": "資料庫表中唯一身份碼列的名稱，通常為Steam十五位ID。",
        "fieldMapId": "使用者資訊對映ID",
        "fieldMapIdAbout": "該ID可以將自定義使用者資訊中的欄位對映到其他記錄，並區分哪些欄位包含所搜尋的字詞，例如名和姓。",
        "friendlyMapping": "簡易對映",
        "tooltipFriendlyMapping": "該功能可以將常見的資料庫表名對映到更簡易的表名。",
        "friendlyMappingExample": "例如: 'drive_license' -> 'Driver's License'",
        "dbValue": "資料庫表明",
        "friendlyValue": "資料庫表明"
      },
      "oneClickInstallation": "Instalación con un clic",
      "manualInstalltion": "Instalação Manual"
    },
    "penal": {
      "createNewPenal": "建立新法律",
      "editPenal": "編輯法律",
      "code": "程式碼",
      "title": "罪名",
      "chargeType": "犯罪型別",
      "bondType": "保釋型別",
      "bondAmount": "保釋金/罰款金額",
      "jailTime": "監禁時長",
      "confirmRemove": "確定要移除這條法律嗎？",
      "errors": {
        "exists": "錯誤：另一個相同的法律已存在！",
        "duplicate": "錯誤：另一個相同的法律程式碼已存在！",
        "notFound": "錯誤：希望移除的法律不存在！"
      },
      "chargeTypes": "犯罪型別",
      "autoSort": "自動排序",
      "bondTypes": "保釋型別",
      "columns": {
        "action": "操作",
        "charge": "罪名",
        "bond": "保釋金"
      }
    },
    "10Codes": {
      "action": "操作",
      "code": "程式碼"
    },
    "permissions": {
      "permissionKeys": "許可權金鑰",
      "permissionKey": "許可權金鑰",
      "key": "金鑰",
      "permissions": "許可權",
      "accountManagement": "賬戶管理",
      "permissionsGuide": "許可權指導",
      "keyName": "金鑰",
      "account": "賬戶",
      "joined": "已加入",
      "pagePermissions": "頁面許可權",
      "unitGeneral": "單位 - 普通",
      "policeAdvanced": "執法部門 - 進階",
      "emsAdvanced": "急救部門 - 進階",
      "fireAdvanced": "消防部門 - 進階",
      "dmvRecords": "車管局記錄",
      "modifyStreetSigns": "修改街道標識",
      "lawRecords": "法務記錄",
      "adminAccess": "管理員許可權",
      "kickUser": "踢出使用者",
      "banUser": "禁止使用者",
      "revokeBan": "撤銷禁止",
      "toggles": {
        "editIdent": "編輯個人員警身份",
        "editOtherIdent": "編輯他人員警身份",
        "selfDispatch": "自我派遣",
        "supervisor": "主管"
      },
      "confirmKick": "確認要剔除",
      "confirmBan": "確定要",
      "confirmRemoveKey": "確認要刪除這個許可權金鑰？",
      "ban": "禁止",
      "unban": "解禁",
      "status": {
        "pending": "待認證",
        "active": "已啟用",
        "banned": "已禁止"
      },
      "errors": {
        "duplicateKey": "錯誤：另一個相同名稱的金鑰已存在！"
      }
    },
    "addresses": {
      "addresses": "地址"
    },
    "logs": {
      "logs": "記錄",
      "log": "日誌",
      "time": "時間"
    }
  },
  "stationAlert": {
    "stationAlert": "alerta de estación",
    "updateDoors": "bir güncelleştirme kapılar",
    "sendAlert": "envoyerAlerte",
    "sendMessage": "शुभकामना करें",
    "makeSelection": "Fazer Seleção",
    "toneBoard": "Tábua de tom",
    "stationTone": "stationstoon"
  }
}